summarytable/__init__.py
summarytable/summarytable.py
summarytable-0.1.0.data/scripts/summarytable
summarytable-0.1.0.data/scripts/summarytable_ap
summarytable-0.1.0.dist-info/LICENSE
summarytable-0.1.0.dist-info/METADATA
summarytable-0.1.0.dist-info/WHEEL
summarytable-0.1.0.dist-info/top_level.txt
summarytable-0.1.0.dist-info/RECORD
