Metadata-Version: 2.1
Name: summarytable
Version: 0.1.0
Summary: Gathering MX processing summaries
Home-page: https://www.github.com/dalekreitler-bnl/summarytable
Author: Dale Kreitler
Author-email: dkreitler@bnl.gov
License: LICENSE.txt
Platform: UNKNOWN
Requires-Python: >=3.8
Requires-Dist: xmltodict
